dyntrack-1.1.2.dist-info/LICENSE
dyntrack-1.1.2.dist-info/top_level.txt
dyntrack-1.1.2.dist-info/RECORD
dyntrack-1.1.2.dist-info/WHEEL
dyntrack-1.1.2.dist-info/METADATA
dyntrack/settings.py
dyntrack/__init__.py
dyntrack/vfkm
dyntrack/logging.py
dyntrack/pl.py
dyntrack/DynTrack.py
dyntrack/tl.py
dyntrack/ut.py
dyntrack/tools/__init__.py
dyntrack/tools/vector_field.py
dyntrack/tools/ftle.py
dyntrack/tools/fit_ppt.py
dyntrack/plot/__init__.py
dyntrack/plot/vector_field.py
dyntrack/plot/tracks.py
dyntrack/plot/ftle.py
dyntrack/plot/fit_ppt.py
dyntrack/utils/__init__.py
dyntrack/utils/load_data.py
dyntrack/utils/FTLE.py
