Metadata-Version: 2.1
Name: dyntrack
Version: 1.1.2
Summary: Python package for the study of particle dynamics from 2D tracks
Home-page: https://github.com/LouisFaure/DynTrack
License: UNKNOWN
Platform: UNKNOWN
License-File: LICENSE
Requires-Dist: tqdm (>=4.45.0)
Requires-Dist: numpy (>=1.18.1)
Requires-Dist: numba (>=0.51.2)
Requires-Dist: pandas (>=1.1.1)
Requires-Dist: matplotlib (>=3.2.2)
Requires-Dist: simpleppt (>=1.1)
